bitin/__init__.py
bitin/basic.py
bitin/universal.py
bitin-0.1.dist-info/METADATA
bitin-0.1.dist-info/WHEEL
bitin-0.1.dist-info/top_level.txt
bitin-0.1.dist-info/RECORD
