Metadata-Version: 2.1
Name: bitin
Version: 0.1
Summary: Digital Electronics Library
Home-page: https://github.com/hexronuspi/bitin/
Author: Aditya
